Metadata-Version: 2.1
Name: easy-llms
Version: 0.1.13
Summary: Easy '1-line' calling of every LLM from OpenAI, MS Azure, AWS Bedrock, GCP Vertex, and Ollama
Home-page: https://github.com/ventz/easy-llms
Author: Ventz Petkov
License: MIT
Classifier: Programming Language :: Python :: 3
Classifier: License :: OSI Approved :: MIT License
Classifier: Operating System :: OS Independent
Requires-Python: >=3.6
License-File: LICENSE
Requires-Dist: langchain ==0.2.11
Requires-Dist: langchain-community
Requires-Dist: langchain-openai
Requires-Dist: langchain-aws
Requires-Dist: langchain-google-vertexai
Requires-Dist: python-dotenv
Requires-Dist: boto3
